dfsx/__init__.py
dfsx/cli.py
dfsx/utils.py
dfsx/script/__init__.py
dfsx/script/app.py
dfsx/script/requirements.txt
dfsx/script/saved_posts.json
dfsx/script/userbot.py
dfsx/script/values.json
dfsx/script/verifieds.json
dfsx-1.6.dist-info/licenses/LICENSE
dfsx-1.6.dist-info/METADATA
dfsx-1.6.dist-info/WHEEL
dfsx-1.6.dist-info/entry_points.txt
dfsx-1.6.dist-info/top_level.txt
dfsx-1.6.dist-info/RECORD
