Metadata-Version: 2.4
Name: dfsx
Version: 1.6
Summary: A CLI tool for setting up and running Telegram bot scripts
Home-page: https://github.com/dfsxteam/dfsx
Author: DFSX Team
Author-email: DFSX Team <contact@dfsx.com>
License: MIT License
Keywords: telegram,bot,cli,automation
Classifier: Development Status :: 4 - Beta
Classifier: Intended Audience :: Developers
Classifier: License :: OSI Approved :: MIT License
Classifier: Operating System :: OS Independent
Classifier: Programming Language :: Python :: 3
Classifier: Programming Language :: Python :: 3.8
Classifier: Programming Language :: Python :: 3.9
Classifier: Programming Language :: Python :: 3.10
Classifier: Programming Language :: Python :: 3.11
Requires-Python: >=3.8
License-File: LICENSE
Requires-Dist: supercore
Dynamic: author
Dynamic: home-page
Dynamic: license-file
Dynamic: requires-python
